brkraw/__init__.py
brkraw/lib/__init__.py
brkraw/lib/backup.py
brkraw/lib/loader.py
brkraw/lib/orient.py
brkraw/lib/parser.py
brkraw/lib/pvobj.py
brkraw/lib/reference.py
brkraw/lib/utils.py
brkraw/scripts/__init__.py
brkraw/scripts/brk_backup.py
brkraw/scripts/brkraw.py
brkraw/ui/__init__.py
brkraw/ui/config.py
brkraw/ui/main_win.py
brkraw/ui/previewer.py
brkraw/ui/scan_info.py
brkraw/ui/scan_list.py
brkraw/ui/subj_info.py
tests/__init__.py
bruker-0.3.7.dist-info/LICENSE
bruker-0.3.7.dist-info/METADATA
bruker-0.3.7.dist-info/WHEEL
bruker-0.3.7.dist-info/entry_points.txt
bruker-0.3.7.dist-info/top_level.txt
bruker-0.3.7.dist-info/RECORD
